{
  "resolvedId": "/home/jdupre/code/kernelquest/www/components/content/NavBar.vue?nuxt_component=async&nuxt_component_name=NavBar",
  "transforms": [
    {
      "name": "vite:load-fallback",
      "result": "<template>\n  <nav class=\"bg-darkest w-100 flex h3 justify-center items-center mb0 pv4\">\n    <div class=\"container h-100 flex items-center justify-between\">\n      <a\n        href=\"/\"\n        class=\"link pv0 mr3 grow flex items-center h-100\">\n        <img src=\"/kernelquest-horizontal-white.svg\" class=\"h2 pt2\"/>\n      </a>\n      <div class=\"flex justify-end items-center w-100 h-100 pt1\">\n        <div class=\"h-100 flex items-center mh4 f6\">\n          <a\n            href=\"/blog\"\n            class=\"tab link grow mh2 ph2 pv2 white pointer\">\n            Blog\n          </a>\n        </div>\n      </div>\n      <div class=\"flex items-center\">\n        <div class=\"mv0 pv0 flex-auto tr flex flex-row justify-end items-center h-100 \">\n          <a\n            href=\"https://play.kernel.quest\"\n            class=\"tab link grow mh2 ph3 pv2 white pointer button\">\n            Playtest\n          </a>\n        </div>\n      </div>\n    </div>\n  </nav>\n</template>\n\n<!-- <script lang=\"ts\">\n  import * as v from '@auth0/auth0-vue';\n\n  console.log('v', v);\n\n  export default {\n    setup() {\n      const { user, isAuthenticated } = v.useAuth0();\n\n      return {\n        user,\n        isAuthenticated\n      };\n    }\n  };\n</script> -->\n",
      "start": 1709737161895,
      "end": 1709737161947,
      "sourcemaps": null
    },
    {
      "name": "nuxt:layer-aliasing",
      "start": 1709737161947,
      "end": 1709737161947,
      "order": "pre"
    },
    {
      "name": "nuxt:layer-aliasing",
      "start": 1709737161947,
      "end": 1709737161947,
      "order": "pre"
    },
    {
      "name": "nuxt:server-devonly:transform",
      "start": 1709737161947,
      "end": 1709737161947,
      "order": "pre"
    },
    {
      "name": "nuxt:server-devonly:transform",
      "start": 1709737161947,
      "end": 1709737161947,
      "order": "pre"
    },
    {
      "name": "content-slot",
      "start": 1709737161947,
      "end": 1709737161947,
      "order": "pre"
    },
    {
      "name": "content-slot",
      "start": 1709737161947,
      "end": 1709737161947,
      "order": "pre"
    },
    {
      "name": "nuxt:client-fallback-auto-id",
      "start": 1709737161947,
      "end": 1709737161947,
      "order": "pre"
    },
    {
      "name": "vite:css",
      "start": 1709737161947,
      "end": 1709737161947,
      "order": "normal"
    },
    {
      "name": "vite:esbuild",
      "start": 1709737161947,
      "end": 1709737161947,
      "order": "normal"
    },
    {
      "name": "vite:json",
      "start": 1709737161947,
      "end": 1709737161947,
      "order": "normal"
    },
    {
      "name": "vite:worker",
      "start": 1709737161947,
      "end": 1709737161947,
      "order": "normal"
    },
    {
      "name": "vite:vue",
      "result": "const _sfc_main = {}\nimport { mergeProps as _mergeProps } from \"vue\"\nimport { ssrRenderAttr as _ssrRenderAttr, ssrRenderAttrs as _ssrRenderAttrs } from \"vue/server-renderer\"\nimport _imports_0 from '/kernelquest-horizontal-white.svg'\n\n\nfunction _sfc_ssrRender(_ctx, _push, _parent, _attrs) {\n  _push(`<nav${\n    _ssrRenderAttrs(_mergeProps({ class: \"bg-darkest w-100 flex h3 justify-center items-center mb0 pv4\" }, _attrs))\n  }><div class=\"container h-100 flex items-center justify-between\"><a href=\"/\" class=\"link pv0 mr3 grow flex items-center h-100\"><img${\n    _ssrRenderAttr(\"src\", _imports_0)\n  } class=\"h2 pt2\"></a><div class=\"flex justify-end items-center w-100 h-100 pt1\"><div class=\"h-100 flex items-center mh4 f6\"><a href=\"/blog\" class=\"tab link grow mh2 ph2 pv2 white pointer\"> Blog </a></div></div><div class=\"flex items-center\"><div class=\"mv0 pv0 flex-auto tr flex flex-row justify-end items-center h-100\"><a href=\"https://play.kernel.quest\" class=\"tab link grow mh2 ph3 pv2 white pointer button\"> Playtest </a></div></div></div></nav>`)\n}\n\n\nimport { useSSRContext as __vite_useSSRContext } from 'vue'\nconst _sfc_setup = _sfc_main.setup\n_sfc_main.setup = (props, ctx) => {\n  const ssrContext = __vite_useSSRContext()\n  ;(ssrContext.modules || (ssrContext.modules = new Set())).add(\"components/content/NavBar.vue\")\n  return _sfc_setup ? _sfc_setup(props, ctx) : undefined\n}\nimport _export_sfc from '\u0000plugin-vue:export-helper'\nexport default /*#__PURE__*/_export_sfc(_sfc_main, [['ssrRender',_sfc_ssrRender]])",
      "start": 1709737161947,
      "end": 1709737161948,
      "order": "normal",
      "sourcemaps": {
        "version": 3,
        "sources": [
          "/home/jdupre/code/kernelquest/www/components/content/NavBar.vue"
        ],
        "names": [],
        "mappings": ";;OAMa,UAAuC;;;;EANpD;IAAA,gBAAA,cACO,KAAK,EAAC,8DAA8D,IAD3E;;IAAA,eAMa,KAAuC,EAAvC,UAAuC",
        "sourcesContent": [
          "<template>\n  <nav class=\"bg-darkest w-100 flex h3 justify-center items-center mb0 pv4\">\n    <div class=\"container h-100 flex items-center justify-between\">\n      <a\n        href=\"/\"\n        class=\"link pv0 mr3 grow flex items-center h-100\">\n        <img src=\"/kernelquest-horizontal-white.svg\" class=\"h2 pt2\"/>\n      </a>\n      <div class=\"flex justify-end items-center w-100 h-100 pt1\">\n        <div class=\"h-100 flex items-center mh4 f6\">\n          <a\n            href=\"/blog\"\n            class=\"tab link grow mh2 ph2 pv2 white pointer\">\n            Blog\n          </a>\n        </div>\n      </div>\n      <div class=\"flex items-center\">\n        <div class=\"mv0 pv0 flex-auto tr flex flex-row justify-end items-center h-100 \">\n          <a\n            href=\"https://play.kernel.quest\"\n            class=\"tab link grow mh2 ph3 pv2 white pointer button\">\n            Playtest\n          </a>\n        </div>\n      </div>\n    </div>\n  </nav>\n</template>\n\n<!-- <script lang=\"ts\">\n  import * as v from '@auth0/auth0-vue';\n\n  console.log('v', v);\n\n  export default {\n    setup() {\n      const { user, isAuthenticated } = v.useAuth0();\n\n      return {\n        user,\n        isAuthenticated\n      };\n    }\n  };\n</script> -->\n"
        ]
      }
    },
    {
      "name": "vite:vue-jsx",
      "start": 1709737161948,
      "end": 1709737161948,
      "order": "normal"
    },
    {
      "name": "replace",
      "start": 1709737161948,
      "end": 1709737161948,
      "order": "normal"
    },
    {
      "name": "replace",
      "start": 1709737161948,
      "end": 1709737161948,
      "order": "normal"
    },
    {
      "name": "nuxt:remove-plugin-metadata",
      "start": 1709737161948,
      "end": 1709737161948,
      "order": "normal"
    },
    {
      "name": "nuxt:remove-plugin-metadata",
      "start": 1709737161948,
      "end": 1709737161948,
      "order": "normal"
    },
    {
      "name": "nuxt:components:imports",
      "result": "import { defineAsyncComponent } from \"vue\"\nexport default defineAsyncComponent(() => import(\"/home/jdupre/code/kernelquest/www/components/content/NavBar.vue\").then(r => r.default))",
      "start": 1709737161948,
      "end": 1709737161948,
      "order": "normal",
      "sourcemaps": null
    },
    {
      "name": "replace",
      "start": 1709737161948,
      "end": 1709737161948,
      "order": "normal"
    },
    {
      "name": "ssr-styles",
      "start": 1709737161948,
      "end": 1709737161948,
      "order": "normal"
    },
    {
      "name": "vite:define",
      "start": 1709737161948,
      "end": 1709737161948,
      "order": "normal"
    },
    {
      "name": "vite:css-post",
      "start": 1709737161948,
      "end": 1709737161948,
      "order": "normal"
    },
    {
      "name": "vite:build-html",
      "start": 1709737161948,
      "end": 1709737161948,
      "order": "normal"
    },
    {
      "name": "vite:worker-import-meta-url",
      "start": 1709737161948,
      "end": 1709737161948,
      "order": "normal"
    },
    {
      "name": "vite:asset-import-meta-url",
      "start": 1709737161948,
      "end": 1709737161948,
      "order": "normal"
    },
    {
      "name": "commonjs",
      "start": 1709737161948,
      "end": 1709737161948,
      "order": "normal"
    },
    {
      "name": "vite:dynamic-import-vars",
      "start": 1709737161948,
      "end": 1709737161948,
      "order": "normal"
    },
    {
      "name": "vite:import-glob",
      "start": 1709737161948,
      "end": 1709737161948,
      "order": "normal"
    },
    {
      "name": "nuxt:composable-keys",
      "start": 1709737161948,
      "end": 1709737161948,
      "order": "post"
    },
    {
      "name": "nuxt:composable-keys",
      "start": 1709737161948,
      "end": 1709737161948,
      "order": "post"
    },
    {
      "name": "nuxt:imports-transform",
      "start": 1709737161948,
      "end": 1709737161948,
      "order": "post"
    },
    {
      "name": "nuxt:imports-transform",
      "start": 1709737161948,
      "end": 1709737161948,
      "order": "post"
    },
    {
      "name": "unctx:transform",
      "start": 1709737161948,
      "end": 1709737161948,
      "order": "post"
    },
    {
      "name": "unctx:transform",
      "start": 1709737161948,
      "end": 1709737161948,
      "order": "post"
    },
    {
      "name": "nuxt:pages-macros-transform",
      "start": 1709737161948,
      "end": 1709737161948,
      "order": "post"
    },
    {
      "name": "nuxt:pages-macros-transform",
      "start": 1709737161948,
      "end": 1709737161948,
      "order": "post"
    },
    {
      "name": "nuxt:tree-shake-template",
      "start": 1709737161948,
      "end": 1709737161948,
      "order": "post"
    },
    {
      "name": "nuxt:components-loader",
      "start": 1709737161948,
      "end": 1709737161948,
      "order": "post"
    },
    {
      "name": "nuxt:tree-shake-composables:transform",
      "start": 1709737161948,
      "end": 1709737161948,
      "order": "post"
    },
    {
      "name": "vite:build-import-analysis",
      "start": 1709737161948,
      "end": 1709737161948,
      "order": "normal"
    },
    {
      "name": "vite:reporter",
      "start": 1709737161948,
      "end": 1709737161948,
      "order": "normal"
    }
  ]
}
